exonware/__init__.py
exonware/xwformats/__init__.py
exonware/xwformats/converter.py
exonware/xwformats/version.py
exonware/xwformats/formats/__init__.py
exonware/xwformats/formats/binary/__init__.py
exonware/xwformats/formats/binary/bson.py
exonware/xwformats/formats/binary/ubjson.py
exonware/xwformats/formats/database/__init__.py
exonware/xwformats/formats/database/graphdb.py
exonware/xwformats/formats/database/leveldb.py
exonware/xwformats/formats/database/lmdb.py
exonware/xwformats/formats/schema/__init__.py
exonware/xwformats/formats/schema/avro.py
exonware/xwformats/formats/schema/capnproto.py
exonware/xwformats/formats/schema/flatbuffers.py
exonware/xwformats/formats/schema/orc.py
exonware/xwformats/formats/schema/parquet.py
exonware/xwformats/formats/schema/protobuf.py
exonware/xwformats/formats/schema/thrift.py
exonware/xwformats/formats/scientific/__init__.py
exonware/xwformats/formats/scientific/feather.py
exonware/xwformats/formats/scientific/hdf5.py
exonware/xwformats/formats/scientific/mat.py
exonware/xwformats/formats/scientific/netcdf.py
exonware/xwformats/formats/scientific/zarr.py
exonware/xwformats/formats/text/__init__.py
exonware/xwformats/formats/text/csv.py
exonware/xwformats/formats/text/toml.py
exonware/xwformats/formats/text/xml.py
exonware/xwformats/formats/text/yaml.py
exonware_xwformats-0.1.0.1.dist-info/METADATA
exonware_xwformats-0.1.0.1.dist-info/WHEEL
exonware_xwformats-0.1.0.1.dist-info/licenses/LICENSE
exonware_xwformats-0.1.0.1.dist-info/RECORD
