Metadata-Version: 2.4
Name: exonware-xwformats
Version: 0.1.0.1
Summary: Enterprise serialization formats for xwsystem - Parquet, Avro, HDF5, NetCDF, and 14 more heavyweight formats
Project-URL: Homepage, https://exonware.com
Project-URL: Repository, https://github.com/exonware/xwformats
Project-URL: Documentation, https://github.com/exonware/xwformats#readme
Author-email: "Eng. Muhammad AlShehri" <connect@exonware.com>
License: MIT
License-File: LICENSE
Keywords: avro,enterprise,exonware,formats,hdf5,netcdf,parquet,protobuf,scientific,serialization,thrift
Classifier: Development Status :: 4 - Beta
Classifier: Intended Audience :: Developers
Classifier: Intended Audience :: Science/Research
Classifier: License :: OSI Approved :: MIT License
Classifier: Operating System :: OS Independent
Classifier: Programming Language :: Python :: 3
Classifier: Programming Language :: Python :: 3.12
Classifier: Topic :: Scientific/Engineering
Classifier: Topic :: Software Development :: Libraries :: Python Modules
Requires-Python: >=3.12
Requires-Dist: exonware-xwsystem>=0.0.1
Provides-Extra: full
Requires-Dist: exonware-xwsystem[full]; extra == 'full'
Requires-Dist: fastavro>=1.4.0; extra == 'full'
Requires-Dist: flatbuffers>=2.0.0; extra == 'full'
Requires-Dist: h5py>=3.8.0; extra == 'full'
Requires-Dist: lmdb>=1.4.0; extra == 'full'
Requires-Dist: lxml>=4.9.0; extra == 'full'
Requires-Dist: neo4j>=4.4.0; extra == 'full'
Requires-Dist: netcdf4>=1.6.0; extra == 'full'
Requires-Dist: numpy>=1.20.0; extra == 'full'
Requires-Dist: pandas>=1.3.0; extra == 'full'
Requires-Dist: protobuf>=3.19.0; extra == 'full'
Requires-Dist: py-ubjson>=0.16.0; extra == 'full'
Requires-Dist: pyarrow>=8.0.0; extra == 'full'
Requires-Dist: pycapnp>=1.1.0; extra == 'full'
Requires-Dist: pydgraph>=21.3.0; extra == 'full'
Requires-Dist: pyorc>=0.6.0; extra == 'full'
Requires-Dist: scipy>=1.7.0; extra == 'full'
Requires-Dist: thrift>=0.15.0; extra == 'full'
Requires-Dist: zarr>=2.15.0; extra == 'full'
Provides-Extra: lazy
Requires-Dist: exonware-xwsystem[lazy]>=0.0.1; extra == 'lazy'
